{
    "chassis": {
        "name": "E1070",
        "status_led": {
            "controllable": true,
            "colors": ["green", "amber", "off"]
        },
    "thermal_manager": false,
        "components": [
		{
			"name": "SWCPLD"	
		},
		{
			"name": "Main_BIOS"
		},
		{
			"name": "Backup_BIOS"
		}
        ],
        "fans": [
            {
                "name": "Fantray1_1",
                "speed": {
                    "controllable": true
                },
                "status_led": {
                    "controllable": true,
                    "colors": ["green", "amber","off"]
                }
            },
            {
                "name": "Fantray2_1",
                "speed": {
                    "controllable": true
                },
                "status_led": {
                    "controllable": true,
                    "colors": ["green", "amber","off"]
                }
            },
            {
                "name": "Fantray3_1",
                "speed": {
                    "controllable": true
                },
                "status_led": {
                    "controllable": true,
                    "colors": ["green", "amber","off"]
                }
            },
            {
                "name": "Fantray1_1",
                "speed": {
                    "controllable": true
                },
                "status_led": {
                    "controllable": true,
                    "colors": ["green", "amber","off"]
                }
            },
            {
                "name": "Fantray2_1",
                "speed": {
                    "controllable": true
                },
                "status_led": {
                    "controllable": true,
                    "colors": ["green", "amber","off"]
                }
            },
            {
                "name": "Fantray3_1",
                "speed": {
                    "controllable": true
                },
                "status_led": {
                    "controllable": true,
                    "colors": ["green", "amber","off"]
                }
            }
        ],
        "fan_drawers": [
            {
                "name": "Fantray1",
                "speed": {
                    "controllable": false
                },
                "status_led": {
                    "controllable": false
                },
		"max_consumed_power": false,
                "fans": [
                    {
                        "name": "Fantray1_1",
                        "speed": {
                            "controllable": false
                        },
                        "status_led": {
                            "controllable": false
                        }
                    }
                ]
            },
            {
                "name": "Fantray2",
                "speed": {
                    "controllable": false
                },
                "status_led": {
                    "controllable": false
                },
		"max_consumed_power": false,
                "fans": [
                    {
                        "name": "Fantray2_1",
                        "speed": {
                            "controllable": false
                        },
                        "status_led": {
                            "controllable": false
                        }
                    }
                ]
            },
            {
                "name": "Fantray3",
                "speed": {
                    "controllable": false
                },
                "status_led": {
                    "controllable": false
                },
		"max_consumed_power": false,
                "fans": [
                    {
                        "name": "Fantray3_1",
                        "speed": {
                            "controllable": false
                        },
                        "status_led": {
                            "controllable": false
                        }
                    }
                ]
            }
        ],
        "psus": [
            {
                "name": "PSU1",
                "fans": [
                    {
                        "name": "PSU1_FAN1",
                        "speed": {
                            "controllable": false
                        },
                        "status_led": {
                            "controllable": false
                        }
                    }
                ],
		"current": true,
                "power": true,
                "max_power": false,
                "voltage_high_threshold": false,
                "voltage_low_threshold": false,
                "temperature": false,
                "fans_target_speed": false,
                "status_led": {
                    "controllable": false
                }
            },
            {
                "name": "PSU2",
                "fans": [
                    {
                        "name": "PSU2_FAN1",
                        "speed": {
                            "controllable": false
                        },
                        "status_led": {
                            "controllable": false
                        }
                    }
                ],
		"current": true,
                "power": true,
                "max_power": false,
                "voltage_high_threshold": false,
                "voltage_low_threshold": false,
                "temperature": false,
                "fans_target_speed": false,
                "status_led": {
                    "controllable": false
                }
            }
        ],
        "thermals": [
            {
                "name": "LM75_U10",
                "controllable": false,
                "low-threshold": false,
                "low-crit-threshold": true
            },
            {
                "name": "LM75_U4",
                "controllable": false,
                "low-threshold": false,
                "low-crit-threshold": true
            },
            {
                "name": "LM75_U7",
                "controllable": false,
                "low-threshold": false,
                "low-crit-threshold": true
            },
            {
                "name": "LM75_U60",
                "controllable": false,
                "low-threshold": false,
                "low-crit-threshold": true
            }
        ],
        "sfps": [
            {
                "name": "PORT0"
            },
            {
                "name": "PORT1"
            },
            {
                "name": "PORT2"
            },
            {
                "name": "PORT3"
            },
            {
                "name": "PORT4"
            },
            {
                "name": "PORT5"
            },
            {
                "name": "PORT6"
            },
            {
                "name": "PORT7"
            },
            {
                "name": "PORT8"
            },
            {
                "name": "PORT9"
            },
            {
                "name": "PORT10"
            },
            {
                "name": "PORT11"
            },
            {
                "name": "PORT12"
            },
            {
                "name": "PORT13"
            },
            {
                "name": "PORT14"
            },
            {
                "name": "PORT15"
            },
            {
                "name": "PORT16"
            },
            {
                "name": "PORT17"
            },
            {
                "name": "PORT18"
            },
            {
                "name": "PORT19"
            },
            {
                "name": "PORT20"
            },
            {
                "name": "PORT21"
            },
            {
                "name": "PORT22"
            },
            {
                "name": "PORT23"
            },
            {
                "name": "PORT24"
            },
            {
                "name": "PORT25"
            },
            {
                "name": "PORT26"
            },
            {
                "name": "PORT27"
            },
            {
                "name": "PORT28"
            },
            {
                "name": "PORT29"
            },
            {
                "name": "PORT30"
            },
            {
                "name": "PORT31"
            },
            {
                "name": "PORT32"
            },
            {
                "name": "PORT33"
            },
            {
                "name": "PORT34"
            },
            {
                "name": "PORT35"
            },
            {
                "name": "PORT36"
            },
            {
                "name": "PORT37"
            },
            {
                "name": "PORT38"
            },
            {
                "name": "PORT39"
            },
            {
                "name": "PORT40"
            },
            {
                "name": "PORT41"
            },
            {
                "name": "PORT42"
            },
            {
                "name": "PORT43"
            },
            {
                "name": "PORT44"
            },
            {
                "name": "PORT45"
            },
            {
                "name": "PORT46"
            },
            {
                "name": "PORT47"
            },
            {
                "name": "PORT48"
            },
            {
                "name": "PORT49"
            },
            {
                "name": "PORT50"
            },
            {
                "name": "PORT51"
            },
            {
                "name": "PORT52"
            },
            {
                "name": "PORT53"
            },
            {
                "name": "PORT54"
            },
            {
                "name": "PORT55"
            }
        ]
    },
    "interfaces": {}
}
